nonebot_plugin_revolver/__init__.py
nonebot_plugin_revolver/config.py
nonebot_plugin_revolver-1.1.2.dist-info/LICENSE
nonebot_plugin_revolver-1.1.2.dist-info/METADATA
nonebot_plugin_revolver-1.1.2.dist-info/WHEEL
nonebot_plugin_revolver-1.1.2.dist-info/RECORD
