Metadata-Version: 2.3
Name: nonebot_plugin_revolver
Version: 1.1.2
Summary: 一个用于 NoneBot 的插件，提供简易左轮禁言小游戏功能，适用于群聊娱乐，支持随机禁言机制。
License: MIT
Keywords: nonebot,plugin,revolver,game,mute,chatbot
Author: xingzhiyou
Requires-Python: >=3.8,<4.0
Classifier: License :: OSI Approved :: MIT License
Classifier: Programming Language :: Python :: 3
Classifier: Programming Language :: Python :: 3.8
Classifier: Programming Language :: Python :: 3.9
Classifier: Programming Language :: Python :: 3.10
Classifier: Programming Language :: Python :: 3.11
Classifier: Programming Language :: Python :: 3.12
Classifier: Programming Language :: Python :: 3.13
Requires-Dist: nonebot-adapter-onebot (>=2.0.0,<3.0.0)
Requires-Dist: nonebot2 (>=2.3.0,<3.0.0)
Project-URL: Homepage, https://github.com/xingzhiyou/nonebot-plugin-revolver
Project-URL: Repository, https://github.com/xingzhiyou/nonebot-plugin-revolver
